market_data_orchestrator/__init__.py
market_data_orchestrator/feedback.py
market_data_orchestrator/health.py
market_data_orchestrator/launcher.py
market_data_orchestrator/logging_config.py
market_data_orchestrator/orchestrator.py
market_data_orchestrator/protocols.py
market_data_orchestrator/settings.py
market_data_orchestrator/_internal/__init__.py
market_data_orchestrator/_internal/container.py
market_data_orchestrator/_internal/control_service.py
market_data_orchestrator/_internal/lifecycle.py
market_data_orchestrator/_internal/rate_limiter.py
market_data_orchestrator/_internal/registry.py
market_data_orchestrator/_internal/status_aggregator.py
market_data_orchestrator/api/__init__.py
market_data_orchestrator/api/auth.py
market_data_orchestrator/api/auth_jwt.py
market_data_orchestrator/api/bundles.py
market_data_orchestrator/api/control.py
market_data_orchestrator/api/deps.py
market_data_orchestrator/api/federation.py
market_data_orchestrator/api/rate_limit.py
market_data_orchestrator/api/websocket.py
market_data_orchestrator/audit/__init__.py
market_data_orchestrator/audit/logger.py
market_data_orchestrator/bundles/__init__.py
market_data_orchestrator/bundles/main.py
market_data_orchestrator/bundles/core/__init__.py
market_data_orchestrator/bundles/core/bundle_loader.py
market_data_orchestrator/bundles/core/http_client.py
market_data_orchestrator/bundles/core/prometheus.py
market_data_orchestrator/bundles/core/scheduler.py
market_data_orchestrator/bundles/jobs/__init__.py
market_data_orchestrator/bundles/jobs/replay_bundle_executor.py
market_data_orchestrator/config/__init__.py
market_data_orchestrator/config/feedback.py
market_data_orchestrator/config/infrastructure.py
market_data_orchestrator/config/provider.py
market_data_orchestrator/config/runtime.py
market_data_orchestrator/config/security.py
market_data_orchestrator/config/unified.py
market_data_orchestrator/events/__init__.py
market_data_orchestrator/events/handler.py
market_data_orchestrator-0.9.3.dist-info/licenses/LICENSE
market_data_orchestrator-0.9.3.dist-info/METADATA
market_data_orchestrator-0.9.3.dist-info/WHEEL
market_data_orchestrator-0.9.3.dist-info/entry_points.txt
market_data_orchestrator-0.9.3.dist-info/top_level.txt
market_data_orchestrator-0.9.3.dist-info/RECORD
