Metadata-Version: 2.4
Name: market_data_orchestrator
Version: 0.9.3
Summary: Orchestration service with bundle-based automation for replay & export workflows
Author-email: Matt Jeffcoat <matt@example.com>
License-Expression: MIT
Classifier: Programming Language :: Python :: 3
Classifier: Programming Language :: Python :: 3.11
Requires-Python: >=3.11
License-File: LICENSE
Requires-Dist: market-data-core==1.4.61
Requires-Dist: market-data-store==0.6.73
Requires-Dist: market-data-pipeline==0.8.69
Requires-Dist: market-data-ibkr==1.1.5
Requires-Dist: fastapi>=0.104.0
Requires-Dist: uvicorn[standard]>=0.24.0
Requires-Dist: pydantic-settings>=2.0.0
Requires-Dist: prometheus-client>=0.19.0
Requires-Dist: python-dotenv>=1.0.0
Requires-Dist: core-registry-client>=0.1.0
Provides-Extra: dev
Requires-Dist: pytest>=7.4.0; extra == "dev"
Requires-Dist: pytest-asyncio>=0.21.0; extra == "dev"
Requires-Dist: pytest-cov>=4.1.0; extra == "dev"
Requires-Dist: black>=23.0.0; extra == "dev"
Requires-Dist: ruff>=0.1.0; extra == "dev"
Requires-Dist: mypy>=1.7.0; extra == "dev"
Dynamic: license-file
